testwizard/set_top_box/SetTopBox.py
testwizard/set_top_box/__init__.py
testwizard.set_top_box-3.8.1.dist-info/LICENSE.txt
testwizard.set_top_box-3.8.1.dist-info/METADATA
testwizard.set_top_box-3.8.1.dist-info/WHEEL
testwizard.set_top_box-3.8.1.dist-info/top_level.txt
testwizard.set_top_box-3.8.1.dist-info/RECORD
