Metadata-Version: 2.1
Name: testwizard.set-top-box
Version: 3.8.1
Summary: Testwizard for set-top box testobjects
Home-page: https://www.resillion.com/testwizard/
Author: Resillion - Belgium
Author-email: testwizard-support@resillion.com
License: UNKNOWN
Platform: UNKNOWN
Classifier: Programming Language :: Python :: 3.3
Classifier: Development Status :: 5 - Production/Stable
Classifier: Operating System :: OS Independent
License-File: LICENSE.txt
Requires-Dist: testwizard.test ==3.8.1
Requires-Dist: testwizard.testobjects-core ==3.8.1
Requires-Dist: testwizard.commands-audio ==3.8.1
Requires-Dist: testwizard.commands-mobile ==3.8.1
Requires-Dist: testwizard.commands-powerswitch ==3.8.1
Requires-Dist: testwizard.commands-remotecontrol ==3.8.1
Requires-Dist: testwizard.commands-video ==3.8.1
